[{"value":"#f9f9fa","type":"color","filePath":"tokens/default.json","isSource":true,"original":{"value":"#f9f9fa","type":"color"},"name":"theme-bg-default","attributes":{"category":"theme","type":"bg","item":"default"},"path":["theme","bg","default"]},{"value":"#2a2f3c","type":"color","filePath":"tokens/default.json","isSource":true,"original":{"value":"#2a2f3c","type":"color"},"name":"theme-bg-header","attributes":{"category":"theme","type":"bg","item":"header"},"path":["theme","bg","header"]},{"value":"#2a2f3c","type":"color","filePath":"tokens/default.json","isSource":true,"original":{"value":"#2a2f3c","type":"color"},"name":"theme-bg-footer","attributes":{"category":"theme","type":"bg","item":"footer"},"path":["theme","bg","footer"]},{"value":"#ffffff","type":"color","filePath":"tokens/default.json","isSource":true,"original":{"value":"#ffffff","type":"color"},"name":"theme-bg-surface","attributes":{"category":"theme","type":"bg","item":"surface"},"path":["theme","bg","surface"]},{"value":"#eeeeee","type":"color","filePath":"tokens/default.json","isSource":true,"original":{"value":"#eeeeee","type":"color"},"name":"theme-bg-surface-alt","attributes":{"category":"theme","type":"bg","item":"surfaceAlt"},"path":["theme","bg","surfaceAlt"]},{"value":"#005f9e","type":"color","filePath":"tokens/default.json","isSource":true,"original":{"value":"#005f9e","type":"color"},"name":"theme-bg-primary","attributes":{"category":"theme","type":"bg","item":"primary"},"path":["theme","bg","primary"]},{"value":"#aeb3bd","type":"color","filePath":"tokens/default.json","isSource":true,"original":{"value":"#aeb3bd","type":"color"},"name":"theme-bg-secondary","attributes":{"category":"theme","type":"bg","item":"secondary"},"path":["theme","bg","secondary"]},{"value":"#ecedf0","type":"color","filePath":"tokens/default.json","isSource":true,"original":{"value":"#ecedf0","type":"color"},"name":"theme-bg-subtle","attributes":{"category":"theme","type":"bg","item":"subtle"},"path":["theme","bg","subtle"]},{"value":"#d0d3d9","type":"color","filePath":"tokens/default.json","isSource":true,"original":{"value":"#d0d3d9","type":"color"},"name":"theme-bg-muted","attributes":{"category":"theme","type":"bg","item":"muted"},"path":["theme","bg","muted"]},{"value":"#000000","type":"color","filePath":"tokens/default.json","isSource":true,"original":{"value":"#000000","type":"color"},"name":"theme-fg-default","attributes":{"category":"theme","type":"fg","item":"default"},"path":["theme","fg","default"]},{"value":"#ffffff","type":"color","filePath":"tokens/default.json","isSource":true,"original":{"value":"#ffffff","type":"color"},"name":"theme-fg-on-accent","attributes":{"category":"theme","type":"fg","item":"onAccent"},"path":["theme","fg","onAccent"]},{"value":"#ecedf0","type":"color","filePath":"tokens/default.json","isSource":true,"original":{"value":"#ecedf0","type":"color"},"name":"theme-fg-on-header","attributes":{"category":"theme","type":"fg","item":"onHeader"},"path":["theme","fg","onHeader"]},{"value":"#d0d3d9","type":"color","filePath":"tokens/default.json","isSource":true,"original":{"value":"#d0d3d9","type":"color"},"name":"theme-fg-on-footer","attributes":{"category":"theme","type":"fg","item":"onFooter"},"path":["theme","fg","onFooter"]},{"value":"#818999","type":"color","filePath":"tokens/default.json","isSource":true,"original":{"value":"#818999","type":"color"},"name":"theme-fg-muted","attributes":{"category":"theme","type":"fg","item":"muted"},"path":["theme","fg","muted"]},{"value":"#aeb3bd","type":"color","filePath":"tokens/default.json","isSource":true,"original":{"value":"#aeb3bd","type":"color"},"name":"theme-fg-subtle","attributes":{"category":"theme","type":"fg","item":"subtle"},"path":["theme","fg","subtle"]},{"value":"#005f9e","type":"color","filePath":"tokens/default.json","isSource":true,"original":{"value":"#005f9e","type":"color"},"name":"theme-fg-link","attributes":{"category":"theme","type":"fg","item":"link"},"path":["theme","fg","link"]},{"value":"#005f9e","type":"color","filePath":"tokens/default.json","isSource":true,"original":{"value":"#005f9e","type":"color"},"name":"theme-button-primary-background","attributes":{"category":"theme","type":"button","item":"primary","subitem":"background"},"path":["theme","button","primary","background"]},{"value":"#000000","type":"color","filePath":"tokens/default.json","isSource":true,"original":{"value":"#000000","type":"color"},"name":"theme-button-ghost-outline","attributes":{"category":"theme","type":"button","item":"ghost","subitem":"outline"},"path":["theme","button","ghost","outline"]},{"value":"#000000","type":"color","filePath":"tokens/default.json","isSource":true,"original":{"value":"#000000","type":"color"},"name":"theme-button-ghost-text","attributes":{"category":"theme","type":"button","item":"ghost","subitem":"text"},"path":["theme","button","ghost","text"]},{"value":4,"type":"borderWidth","filePath":"tokens/default.json","isSource":true,"original":{"value":4,"type":"borderWidth"},"name":"theme-border-width-button-ghost","attributes":{"category":"theme","type":"borderWidth","item":"button","subitem":"ghost"},"path":["theme","borderWidth","button","ghost"]},{"value":0,"type":"borderRadius","filePath":"tokens/default.json","isSource":true,"original":{"value":0,"type":"borderRadius"},"name":"theme-border-radius-button","attributes":{"category":"theme","type":"borderRadius","item":"button"},"path":["theme","borderRadius","button"]},{"value":0,"type":"borderRadius","filePath":"tokens/default.json","isSource":true,"original":{"value":0,"type":"borderRadius"},"name":"theme-border-radius-card","attributes":{"category":"theme","type":"borderRadius","item":"card"},"path":["theme","borderRadius","card"]},{"value":0,"type":"borderRadius","filePath":"tokens/default.json","isSource":true,"original":{"value":0,"type":"borderRadius"},"name":"theme-border-radius-input","attributes":{"category":"theme","type":"borderRadius","item":"input"},"path":["theme","borderRadius","input"]},{"value":"Gotham","type":"fontFamilies","filePath":"tokens/default.json","isSource":true,"original":{"value":"Gotham","type":"fontFamilies"},"name":"theme-font-families-display","attributes":{"category":"theme","type":"fontFamilies","item":"display"},"path":["theme","fontFamilies","display"]},{"value":"Helvetica Neue Condensed","type":"fontFamilies","filePath":"tokens/default.json","isSource":true,"original":{"value":"Helvetica Neue Condensed","type":"fontFamilies"},"name":"theme-font-families-body","attributes":{"category":"theme","type":"fontFamilies","item":"body"},"path":["theme","fontFamilies","body"]},{"value":"Gotham","type":"fontFamilies","filePath":"tokens/default.json","isSource":true,"original":{"value":"Gotham","type":"fontFamilies"},"name":"theme-font-families-nav","attributes":{"category":"theme","type":"fontFamilies","item":"nav"},"path":["theme","fontFamilies","nav"]},{"value":16,"type":"fontSizes","filePath":"tokens/default.json","isSource":true,"original":{"value":16,"type":"fontSizes"},"name":"theme-font-sizes-default","attributes":{"category":"theme","type":"fontSizes","item":"default"},"path":["theme","fontSizes","default"]}]